plover_palantype_german/__init__.py
plover_palantype_german/machine.py
plover_palantype_german/system.py
plover_palantype_german-0.0.25.dist-info/METADATA
plover_palantype_german-0.0.25.dist-info/WHEEL
plover_palantype_german-0.0.25.dist-info/entry_points.txt
plover_palantype_german-0.0.25.dist-info/top_level.txt
plover_palantype_german-0.0.25.dist-info/zip-safe
plover_palantype_german-0.0.25.dist-info/RECORD
