Metadata-Version: 2.1
Name: plover-palantype-german
Version: 0.0.25
Summary: Possum Palantype support for Plover for German
Home-page: https://github.com/percidae/plover_palantype
Author: percidae
Author-email: percidae@openmailbox.org
License: GNU General Public License v2 or later (GPLv2+)
Keywords: plover plover_plugin
Platform: UNKNOWN
Classifier: Development Status :: 4 - Beta
Classifier: Environment :: Plugins
Classifier: Intended Audience :: End Users/Desktop
Classifier: License :: OSI Approved :: GNU General Public License v2 or later (GPLv2+)
Classifier: Operating System :: OS Independent
Classifier: Programming Language :: Python :: 3
Classifier: Programming Language :: Python :: 3.6
Requires-Dist: plover (>=4.0.0.dev1)
